README.md
setup.py
sweet/__init__.py
sweet/autotest.py
sweet/banner.py
sweet/config.py
sweet/excel.py
sweet/globals.py
sweet/log.py
sweet/module.py
sweet/parse.py
sweet/push.py
sweet/report.py
sweet/suite.py
sweet/sweet.py
sweet/testcase.py
sweet/utility.py
sweet/vars.py
sweet/lib/__init__.py
sweet/lib/c.py
sweet/lib/http_handle.py
sweet/lib/u.py
sweet/modules/__init__.py
sweet/modules/common.py
sweet/modules/publish.py
sweetest.egg-info/PKG-INFO
sweetest.egg-info/SOURCES.txt
sweetest.egg-info/dependency_links.txt
sweetest.egg-info/requires.txt
sweetest.egg-info/top_level.txt