Metadata-Version: 2.1
Name: sweetest
Version: 1.4.4
Summary: Sweet experience version
Home-page: https://github.com/Sweeterio/sweet
Author: tonglei
Author-email: tonglei@qq.com
License: UNKNOWN
Platform: UNKNOWN
Classifier: Programming Language :: Python :: 3
Classifier: License :: OSI Approved :: MIT License
Classifier: Operating System :: OS Independent
